README.md
license.txt
setup.py
calculator_program/__init__.py
calculator_program/calculator.py
calculator_program.egg-info/PKG-INFO
calculator_program.egg-info/SOURCES.txt
calculator_program.egg-info/dependency_links.txt
calculator_program.egg-info/top_level.txt